{
  "children": [
    {
	  "children": [
      {
        "asian_color": "#4393c3",
        "asian_ej_efficiency": -0.4762320319,
        "black_color": "#d6604d",
        "black_ej_efficiency": 0.5382450112,
        "code": "AA",
        "fracTotalConc": 0.0781510667,
        "latino_color": "#92c5de",
        "latino_ej_efficiency": -0.3709557678,
        "name": "Agricultural Chemical Mfg",
        "nw_color": "#d1e5f0",
        "nw_ej_efficiency": -0.0616320172
      },
      {
        "asian_color": "#d1e5f0",
        "asian_ej_efficiency": -0.1011242823,
        "black_color": "#d6604d",
        "black_ej_efficiency": 0.503484431,
        "code": "AA",
        "fracTotalConc": 0.1399586361,
        "latino_color": "#f4a582",
        "latino_ej_efficiency": 0.2461210151,
        "name": "Inorganic Chemical Mfg",
        "nw_color": "#f4a582",
        "nw_ej_efficiency": 0.2558594093
      },
      {
        "asian_color": "#d1e5f0",
        "asian_ej_efficiency": -0.1532886083,
        "black_color": "#67001f",
        "black_ej_efficiency": 0.9666147459,
        "code": "AA",
        "fracTotalConc": 0.0564996829,
        "latino_color": "#fddbc7",
        "latino_ej_efficiency": 0.0486929449,
        "name": "Organic Chemical Mfg",
        "nw_color": "#f4a582",
        "nw_ej_efficiency": 0.3148165731
      },
      {
        "asian_color": "#fddbc7",
        "asian_ej_efficiency": 0.1094786814,
        "black_color": "#b2182b",
        "black_ej_efficiency": 0.71143982,
        "code": "AA",
        "fracTotalConc": 0.1940576277,
        "latino_color": "#fddbc7",
        "latino_ej_efficiency": 0.1936676562,
        "name": "Other Chemical Mfg",
        "nw_color": "#f4a582",
        "nw_ej_efficiency": 0.3396559558
      },
      {
        "asian_color": "#f4a582",
        "asian_ej_efficiency": 0.3964370764,
        "black_color": "#67001f",
        "black_ej_efficiency": 0.8594384991,
        "code": "AA",
        "fracTotalConc": 0.0102862721,
        "latino_color": "#d6604d",
        "latino_ej_efficiency": 0.5215935443,
        "name": "Paint, Varnish, Lacquer, Enamel Mfg",
        "nw_color": "#d6604d",
        "nw_ej_efficiency": 0.5787241723
      },
      {
        "asian_color": "#67001f",
        "asian_ej_efficiency": 1.5142315545,
        "black_color": "#fddbc7",
        "black_ej_efficiency": 0.0089478586,
        "code": "AA",
        "fracTotalConc": 0.0035912383,
        "latino_color": "#67001f",
        "latino_ej_efficiency": 0.8209561759,
        "name": "Pharmaceutical Mfg",
        "nw_color": "#d6604d",
        "nw_ej_efficiency": 0.5909634941
      },
      {
        "asian_color": "#f4a582",
        "asian_ej_efficiency": 0.3194337386,
        "black_color": "#d6604d",
        "black_ej_efficiency": 0.4303931284,
        "code": "AA",
        "fracTotalConc": 0.0509819258,
        "latino_color": "#b2182b",
        "latino_ej_efficiency": 0.7925937839,
        "name": "Polymer & Resin Mfg",
        "nw_color": "#d6604d",
        "nw_ej_efficiency": 0.553375973
      }
    ],
    "name": "Chemical & Allied Product Mfg"
  },
  {
    "children": [
      {
        "asian_color": "#92c5de",
        "asian_ej_efficiency": -0.338998991,
        "black_color": "#fddbc7",
        "black_ej_efficiency": 0.168322637,
        "code": "AA",
        "fracTotalConc": 8.9979058659,
        "latino_color": "#4393c3",
        "latino_ej_efficiency": -0.4622792155,
        "name": "Coal",
        "nw_color": "#92c5de",
        "nw_ej_efficiency": -0.2203621013
      },
      {
        "asian_color": "#b2182b",
        "asian_ej_efficiency": 0.6887533047,
        "black_color": "#d6604d",
        "black_ej_efficiency": 0.4395769671,
        "code": "AA",
        "fracTotalConc": 0.1627468581,
        "latino_color": "#d6604d",
        "latino_ej_efficiency": 0.4306076157,
        "name": "Gas",
        "nw_color": "#d6604d",
        "nw_ej_efficiency": 0.4438369628
      },
      {
        "asian_color": "#b2182b",
        "asian_ej_efficiency": 0.6585595384,
        "black_color": "#d6604d",
        "black_ej_efficiency": 0.4214526529,
        "code": "AA",
        "fracTotalConc": 0.584644533,
        "latino_color": "#b2182b",
        "latino_ej_efficiency": 0.664089322,
        "name": "Internal Combustion",
        "nw_color": "#d6604d",
        "nw_ej_efficiency": 0.5385763562
      },
      {
        "asian_color": "#67001f",
        "asian_ej_efficiency": 1.0929409468,
        "black_color": "#d1e5f0",
        "black_ej_efficiency": -0.0459020237,
        "code": "AA",
        "fracTotalConc": 0.2984210307,
        "latino_color": "#67001f",
        "latino_ej_efficiency": 0.8134832219,
        "name": "Oil",
        "nw_color": "#d6604d",
        "nw_ej_efficiency": 0.5382575256
      },
      {
        "asian_color": "#d1e5f0",
        "asian_ej_efficiency": -0.1432636138,
        "black_color": "#f4a582",
        "black_ej_efficiency": 0.2612060733,
        "code": "AA",
        "fracTotalConc": 0.0740061954,
        "latino_color": "#fddbc7",
        "latino_ej_efficiency": 0.0296757412,
        "name": "Other",
        "nw_color": "#fddbc7",
        "nw_ej_efficiency": 0.0718353253
      }
    ],
    "name": "Fuel Comb. Elec. Util."
  },
  {
    "children": [
      {
        "asian_color": "#d1e5f0",
        "asian_ej_efficiency": -0.0734710894,
        "black_color": "#fddbc7",
        "black_ej_efficiency": 0.1262020168,
        "code": "AA",
        "fracTotalConc": 1.8732952591,
        "latino_color": "#d1e5f0",
        "latino_ej_efficiency": -0.0393848118,
        "name": "Coal",
        "nw_color": "#fddbc7",
        "nw_ej_efficiency": 0.0104094825
      },
      {
        "asian_color": "#d6604d",
        "asian_ej_efficiency": 0.4961504502,
        "black_color": "#d6604d",
        "black_ej_efficiency": 0.453147207,
        "code": "AA",
        "fracTotalConc": 1.4248765802,
        "latino_color": "#b2182b",
        "latino_ej_efficiency": 0.6369352571,
        "name": "Gas",
        "nw_color": "#d6604d",
        "nw_ej_efficiency": 0.5137457662
      },
      {
        "asian_color": "#d1e5f0",
        "asian_ej_efficiency": -0.0588297693,
        "black_color": "#fddbc7",
        "black_ej_efficiency": 0.0935797807,
        "code": "AA",
        "fracTotalConc": 0.665153777,
        "latino_color": "#fddbc7",
        "latino_ej_efficiency": 0.0992939779,
        "name": "Internal Combustion",
        "nw_color": "#fddbc7",
        "nw_ej_efficiency": 0.0726965607
      },
      {
        "asian_color": "#b2182b",
        "asian_ej_efficiency": 0.7704006255,
        "black_color": "#d6604d",
        "black_ej_efficiency": 0.564941507,
        "code": "AA",
        "fracTotalConc": 0.6951122192,
        "latino_color": "#d6604d",
        "latino_ej_efficiency": 0.4257890392,
        "name": "Oil",
        "nw_color": "#d6604d",
        "nw_ej_efficiency": 0.4882835165
      },
      {
        "asian_color": "#d1e5f0",
        "asian_ej_efficiency": -0.1232965419,
        "black_color": "#67001f",
        "black_ej_efficiency": 0.8036566538,
        "code": "AA",
        "fracTotalConc": 2.2061977102,
        "latino_color": "#fddbc7",
        "latino_ej_efficiency": 0.0265053716,
        "name": "Other",
        "nw_color": "#f4a582",
        "nw_ej_efficiency": 0.2574963984
      }
    ],
    "name": "Fuel Comb. Industrial"
  },
  {
    "children": [
      {
        "asian_color": "#92c5de",
        "asian_ej_efficiency": -0.3612852749,
        "black_color": "#f4a582",
        "black_ej_efficiency": 0.3299992383,
        "code": "AA",
        "fracTotalConc": 0.1050372107,
        "latino_color": "#2166ac",
        "latino_ej_efficiency": -0.6013647311,
        "name": "Commercial/Institutional Coal",
        "nw_color": "#92c5de",
        "nw_ej_efficiency": -0.2370094012
      },
      {
        "asian_color": "#67001f",
        "asian_ej_efficiency": 1.1320476356,
        "black_color": "#d6604d",
        "black_ej_efficiency": 0.5030175019,
        "code": "AA",
        "fracTotalConc": 0.7686645227,
        "latino_color": "#b2182b",
        "latino_ej_efficiency": 0.6708987036,
        "name": "Commercial/Institutional Gas",
        "nw_color": "#b2182b",
        "nw_ej_efficiency": 0.6350916884
      },
      {
        "asian_color": "#67001f",
        "asian_ej_efficiency": 1.1432947703,
        "black_color": "#b2182b",
        "black_ej_efficiency": 0.6534764659,
        "code": "AA",
        "fracTotalConc": 0.1244582273,
        "latino_color": "#d6604d",
        "latino_ej_efficiency": 0.5145203504,
        "name": "Commercial/Institutional Oil",
        "nw_color": "#b2182b",
        "nw_ej_efficiency": 0.6090318868
      },
      {
        "asian_color": "#f4a582",
        "asian_ej_efficiency": 0.3401540729,
        "black_color": "#b2182b",
        "black_ej_efficiency": 0.6118034221,
        "code": "AA",
        "fracTotalConc": 0.2667403229,
        "latino_color": "#d1e5f0",
        "latino_ej_efficiency": -0.0907744696,
        "name": "Misc. Fuel Comb. (Except Residential)",
        "nw_color": "#f4a582",
        "nw_ej_efficiency": 0.2126816893
      },
      {
        "asian_color": "#67001f",
        "asian_ej_efficiency": 1.1024178204,
        "black_color": "#b2182b",
        "black_ej_efficiency": 0.6947427744,
        "code": "AA",
        "fracTotalConc": 2.6457822929,
        "latino_color": "#d6604d",
        "latino_ej_efficiency": 0.521914256,
        "name": "Residential Other",
        "nw_color": "#b2182b",
        "nw_ej_efficiency": 0.6247331819
      },
      {
        "asian_color": "#f4a582",
        "asian_ej_efficiency": 0.2981620005,
        "black_color": "#fddbc7",
        "black_ej_efficiency": 0.0225212662,
        "code": "AA",
        "fracTotalConc": 3.9568729971,
        "latino_color": "#d1e5f0",
        "latino_ej_efficiency": -0.1246376412,
        "name": "Residential Wood",
        "nw_color": "#d1e5f0",
        "nw_ej_efficiency": -0.0083887602
      }
    ],
    "name": "Fuel Comb. Other"
  },
  {
    "children": [
      {
        "asian_color": "#b2182b",
        "asian_ej_efficiency": 0.6339141813,
        "black_color": "#b2182b",
        "black_ej_efficiency": 0.762123664,
        "code": "AA",
        "fracTotalConc": 0.0063119986,
        "latino_color": "#f4a582",
        "latino_ej_efficiency": 0.277925603,
        "name": "Compressed Natural Gas (CNG)",
        "nw_color": "#d6604d",
        "nw_ej_efficiency": 0.4667904932
      },
      {
        "asian_color": "#f4a582",
        "asian_ej_efficiency": 0.3293772746,
        "black_color": "#f4a582",
        "black_ej_efficiency": 0.3172077931,
        "code": "AA",
        "fracTotalConc": 5.819355505,
        "latino_color": "#f4a582",
        "latino_ej_efficiency": 0.2281756159,
        "name": "Diesel Fuel",
        "nw_color": "#f4a582",
        "nw_ej_efficiency": 0.2568063412
      },
      {
        "asian_color": "#d1e5f0",
        "asian_ej_efficiency": -0.0962870647,
        "black_color": "#d6604d",
        "black_ej_efficiency": 0.451868307,
        "code": "AA",
        "fracTotalConc": 0.0032842668,
        "latino_color": "#92c5de",
        "latino_ej_efficiency": -0.2315602071,
        "name": "Ethanol (E-85)",
        "nw_color": "#fddbc7",
        "nw_ej_efficiency": 0.0276113173
      },
      {
        "asian_color": "#d6604d",
        "asian_ej_efficiency": 0.5295693855,
        "black_color": "#f4a582",
        "black_ej_efficiency": 0.3636171434,
        "code": "AA",
        "fracTotalConc": 9.1532848652,
        "latino_color": "#d6604d",
        "latino_ej_efficiency": 0.4150479672,
        "name": "Gasoline",
        "nw_color": "#f4a582",
        "nw_ej_efficiency": 0.3870839807
      }
    ],
    "name": "Highway Vehicles"
  },
  {
    "children": [
      {
        "asian_color": "#92c5de",
        "asian_ej_efficiency": -0.3688896318,
        "black_color": "#b2182b",
        "black_ej_efficiency": 0.7225062479,
        "code": "AA",
        "fracTotalConc": 0.4783906101,
        "latino_color": "#92c5de",
        "latino_ej_efficiency": -0.3699269884,
        "name": "Ferrous Metals Processing",
        "nw_color": "#fddbc7",
        "nw_ej_efficiency": 0.0045383529
      },
      {
        "asian_color": "#d6604d",
        "asian_ej_efficiency": 0.5104863537,
        "black_color": "#f4a582",
        "black_ej_efficiency": 0.2278176581,
        "code": "AA",
        "fracTotalConc": 0.0466924334,
        "latino_color": "#d1e5f0",
        "latino_ej_efficiency": -0.0060798882,
        "name": "Metals Processing NEC",
        "nw_color": "#fddbc7",
        "nw_ej_efficiency": 0.1458101376
      },
      {
        "asian_color": "#67001f",
        "asian_ej_efficiency": 1.372161736,
        "black_color": "#d1e5f0",
        "black_ej_efficiency": -0.0013490013,
        "code": "AA",
        "fracTotalConc": 0.8415118589,
        "latino_color": "#67001f",
        "latino_ej_efficiency": 1.4909350327,
        "name": "Non-Ferrous Metals Processing",
        "nw_color": "#67001f",
        "nw_ej_efficiency": 0.8917672252
      }
    ],
    "name": "Metals Processing"
  },
  {
    "children": [
      {
        "asian_color": "#d1e5f0",
        "asian_ej_efficiency": -0.009149257,
        "black_color": "#fddbc7",
        "black_ej_efficiency": 0.0023627466,
        "code": "AA",
        "fracTotalConc": 13.7153490888,
        "latino_color": "#d1e5f0",
        "latino_ej_efficiency": -0.0275903444,
        "name": "Agriculture & Forestry",
        "nw_color": "#d1e5f0",
        "nw_ej_efficiency": -0.0187655764
      },
      {
        "asian_color": "#f4a582",
        "asian_ej_efficiency": 0.3876601332,
        "black_color": "#d1e5f0",
        "black_ej_efficiency": -0.1103883179,
        "code": "AA",
        "fracTotalConc": 0.0001698521,
        "latino_color": "#d1e5f0",
        "latino_ej_efficiency": -0.1555820997,
        "name": "Catastrophic/Accidental Releases",
        "nw_color": "#d1e5f0",
        "nw_ej_efficiency": -0.0605639287
      },
      {
        "asian_color": "#b2182b",
        "asian_ej_efficiency": 0.6082466639,
        "black_color": "#f4a582",
        "black_ej_efficiency": 0.2132514494,
        "code": "AA",
        "fracTotalConc": 6.08633e-05,
        "latino_color": "#b2182b",
        "latino_ej_efficiency": 0.753697826,
        "name": "Health Services",
        "nw_color": "#d6604d",
        "nw_ej_efficiency": 0.494784348
      },
      {
        "asian_color": "#67001f",
        "asian_ej_efficiency": 1.4651768213,
        "black_color": "#b2182b",
        "black_ej_efficiency": 0.7670882111,
        "code": "AA",
        "fracTotalConc": 0.2514189244,
        "latino_color": "#67001f",
        "latino_ej_efficiency": 0.9287725235,
        "name": "Other",
        "nw_color": "#67001f",
        "nw_ej_efficiency": 0.8815284272
      },
      {
        "asian_color": "#92c5de",
        "asian_ej_efficiency": -0.3750249348,
        "black_color": "#fddbc7",
        "black_ej_efficiency": 0.0574511959,
        "code": "AA",
        "fracTotalConc": 5.4285867633,
        "latino_color": "#d1e5f0",
        "latino_ej_efficiency": -0.1732955633,
        "name": "Other Combustion",
        "nw_color": "#d1e5f0",
        "nw_ej_efficiency": -0.108174585
      },
      {
        "asian_color": "#f4a582",
        "asian_ej_efficiency": 0.2023434741,
        "black_color": "#f4a582",
        "black_ej_efficiency": 0.3165301437,
        "code": "AA",
        "fracTotalConc": 14.3454973703,
        "latino_color": "#f4a582",
        "latino_ej_efficiency": 0.2773338068,
        "name": "Other Fugitive Dust",
        "nw_color": "#f4a582",
        "nw_ej_efficiency": 0.2644994506
      },
      {
        "asian_color": "#4393c3",
        "asian_ej_efficiency": -0.4203011833,
        "black_color": "#67001f",
        "black_ej_efficiency": 1.0665256368,
        "code": "AA",
        "fracTotalConc": 0.0003227788,
        "latino_color": "#4393c3",
        "latino_ej_efficiency": -0.4206797346,
        "name": "Repair Shops",
        "nw_color": "#fddbc7",
        "nw_ej_efficiency": 0.0934152324
      }
    ],
    "name": "Miscellaneous"
  },
  {
    "children": [
      {
        "asian_color": "#b2182b",
        "asian_ej_efficiency": 0.7739394297,
        "black_color": "#b2182b",
        "black_ej_efficiency": 0.7129684572,
        "code": "AA",
        "fracTotalConc": 0.5804264426,
        "latino_color": "#b2182b",
        "latino_ej_efficiency": 0.70046934,
        "name": "Aircraft",
        "nw_color": "#b2182b",
        "nw_ej_efficiency": 0.6803967738
      },
      {
        "asian_color": "#b2182b",
        "asian_ej_efficiency": 0.624982593,
        "black_color": "#f4a582",
        "black_ej_efficiency": 0.271078864,
        "code": "AA",
        "fracTotalConc": 0.9138164652,
        "latino_color": "#d6604d",
        "latino_ej_efficiency": 0.5593079958,
        "name": "Marine Vessels",
        "nw_color": "#d6604d",
        "nw_ej_efficiency": 0.4395301202
      },
      {
        "asian_color": "#d6604d",
        "asian_ej_efficiency": 0.4635958494,
        "black_color": "#f4a582",
        "black_ej_efficiency": 0.3563563834,
        "code": "AA",
        "fracTotalConc": 3.2483147842,
        "latino_color": "#f4a582",
        "latino_ej_efficiency": 0.3217223048,
        "name": "Non-Road Diesel",
        "nw_color": "#f4a582",
        "nw_ej_efficiency": 0.3307006261
      },
      {
        "asian_color": "#67001f",
        "asian_ej_efficiency": 0.9905468046,
        "black_color": "#f4a582",
        "black_ej_efficiency": 0.3106370773,
        "code": "AA",
        "fracTotalConc": 1.4573010836,
        "latino_color": "#b2182b",
        "latino_ej_efficiency": 0.6445489675,
        "name": "Non-Road Gasoline",
        "nw_color": "#d6604d",
        "nw_ej_efficiency": 0.5435051326
      },
      {
        "asian_color": "#d6604d",
        "asian_ej_efficiency": 0.4999958287,
        "black_color": "#f4a582",
        "black_ej_efficiency": 0.3769680578,
        "code": "AA",
        "fracTotalConc": 0.1779164115,
        "latino_color": "#f4a582",
        "latino_ej_efficiency": 0.2922780222,
        "name": "Other",
        "nw_color": "#f4a582",
        "nw_ej_efficiency": 0.3268956492
      },
      {
        "asian_color": "#92c5de",
        "asian_ej_efficiency": -0.2568124029,
        "black_color": "#fddbc7",
        "black_ej_efficiency": 0.0687050185,
        "code": "AA",
        "fracTotalConc": 1.1756014668,
        "latino_color": "#d1e5f0",
        "latino_ej_efficiency": -0.166628356,
        "name": "Railroads",
        "nw_color": "#d1e5f0",
        "nw_ej_efficiency": -0.0955301726
      }
    ],
    "name": "Off-Highway"
  },
  {
    "children": [
      {
        "asian_color": "#b2182b",
        "asian_ej_efficiency": 0.7459638554,
        "black_color": "#d6604d",
        "black_ej_efficiency": 0.5715569935,
        "code": "AA",
        "fracTotalConc": 2.8997164309,
        "latino_color": "#b2182b",
        "latino_ej_efficiency": 0.6578816184,
        "name": "Agriculture, Food, & Kindred Products",
        "nw_color": "#b2182b",
        "nw_ej_efficiency": 0.6033941797
      },
      {
        "asian_color": "#f4a582",
        "asian_ej_efficiency": 0.2442415848,
        "black_color": "#fddbc7",
        "black_ej_efficiency": 0.1596525916,
        "code": "AA",
        "fracTotalConc": 0.0007271159,
        "latino_color": "#f4a582",
        "latino_ej_efficiency": 0.2786492883,
        "name": "Construction",
        "nw_color": "#f4a582",
        "nw_ej_efficiency": 0.2209547318
      },
      {
        "asian_color": "#b2182b",
        "asian_ej_efficiency": 0.6205297179,
        "black_color": "#fddbc7",
        "black_ej_efficiency": 0.038415821,
        "code": "AA",
        "fracTotalConc": 0.0049921742,
        "latino_color": "#67001f",
        "latino_ej_efficiency": 1.4139798207,
        "name": "Electronic Equipment",
        "nw_color": "#b2182b",
        "nw_ej_efficiency": 0.7469440589
      },
      {
        "asian_color": "#fddbc7",
        "asian_ej_efficiency": 0.0383885807,
        "black_color": "#d6604d",
        "black_ej_efficiency": 0.427724818,
        "code": "AA",
        "fracTotalConc": 0.0562466685,
        "latino_color": "#f4a582",
        "latino_ej_efficiency": 0.3065195536,
        "name": "Machinery Products",
        "nw_color": "#f4a582",
        "nw_ej_efficiency": 0.2795641461
      },
      {
        "asian_color": "#fddbc7",
        "asian_ej_efficiency": 0.032324764,
        "black_color": "#fddbc7",
        "black_ej_efficiency": 0.1156952491,
        "code": "AA",
        "fracTotalConc": 1.4744254113,
        "latino_color": "#fddbc7",
        "latino_ej_efficiency": 0.1946202515,
        "name": "Mineral Products",
        "nw_color": "#fddbc7",
        "nw_ej_efficiency": 0.1396317011
      },
      {
        "asian_color": "#67001f",
        "asian_ej_efficiency": 0.811409901,
        "black_color": "#d6604d",
        "black_ej_efficiency": 0.4339236031,
        "code": "AA",
        "fracTotalConc": 0.4408751473,
        "latino_color": "#67001f",
        "latino_ej_efficiency": 0.8570092775,
        "name": "Miscellaneous Industrial Processes",
        "nw_color": "#b2182b",
        "nw_ej_efficiency": 0.653529661
      },
      {
        "asian_color": "#d6604d",
        "asian_ej_efficiency": 0.5912788447,
        "black_color": "#f4a582",
        "black_ej_efficiency": 0.2974408083,
        "code": "AA",
        "fracTotalConc": 0.0557354659,
        "latino_color": "#b2182b",
        "latino_ej_efficiency": 0.6869950186,
        "name": "Rubber & Miscellaneous Plastic Products",
        "nw_color": "#d6604d",
        "nw_ej_efficiency": 0.499609579
      },
      {
        "asian_color": "#67001f",
        "asian_ej_efficiency": 1.0350849307,
        "black_color": "#f4a582",
        "black_ej_efficiency": 0.3008971092,
        "code": "AA",
        "fracTotalConc": 0.0073008321,
        "latino_color": "#f4a582",
        "latino_ej_efficiency": 0.2118731069,
        "name": "Textiles, Leather, & Apparel Products",
        "nw_color": "#f4a582",
        "nw_ej_efficiency": 0.3451267423
      },
      {
        "asian_color": "#d1e5f0",
        "asian_ej_efficiency": -0.0079960942,
        "black_color": "#92c5de",
        "black_ej_efficiency": -0.2667247071,
        "code": "AA",
        "fracTotalConc": 0.013781413,
        "latino_color": "#d6604d",
        "latino_ej_efficiency": 0.4108457402,
        "name": "Transportation Equipment",
        "nw_color": "#fddbc7",
        "nw_ej_efficiency": 0.1117039511
      },
      {
        "asian_color": "#d6604d",
        "asian_ej_efficiency": 0.4922986332,
        "black_color": "#d6604d",
        "black_ej_efficiency": 0.4981592752,
        "code": "AA",
        "fracTotalConc": 0.4525601387,
        "latino_color": "#d6604d",
        "latino_ej_efficiency": 0.5242236171,
        "name": "Wood, Pulp & Paper, & Publishing Products",
        "nw_color": "#d6604d",
        "nw_ej_efficiency": 0.4788722851
      }
    ],
    "name": "Other Industrial Processes"
  },
  {
    "children": [
      {
        "asian_color": "#b2182b",
        "asian_ej_efficiency": 0.65995924,
        "black_color": "#d6604d",
        "black_ej_efficiency": 0.4893061347,
        "code": "AA",
        "fracTotalConc": 0.0590359108,
        "latino_color": "#b2182b",
        "latino_ej_efficiency": 0.7210398517,
        "name": "Asphalt Manufacturing",
        "nw_color": "#d6604d",
        "nw_ej_efficiency": 0.5904392895
      },
      {
        "asian_color": "#92c5de",
        "asian_ej_efficiency": -0.3493382014,
        "black_color": "#d1e5f0",
        "black_ej_efficiency": -0.1682445254,
        "code": "AA",
        "fracTotalConc": 1.704298585,
        "latino_color": "#fddbc7",
        "latino_ej_efficiency": 0.103197667,
        "name": "Oil & Gas Production",
        "nw_color": "#d1e5f0",
        "nw_ej_efficiency": -0.0500036723
      },
      {
        "asian_color": "#d6604d",
        "asian_ej_efficiency": 0.4949284733,
        "black_color": "#b2182b",
        "black_ej_efficiency": 0.6880432461,
        "code": "AA",
        "fracTotalConc": 0.291030989,
        "latino_color": "#67001f",
        "latino_ej_efficiency": 0.8304556989,
        "name": "Petroleum Refineries & Related Industries",
        "nw_color": "#b2182b",
        "nw_ej_efficiency": 0.6844500975
      }
    ],
    "name": "Petroleum & Related Industries"
  },
  {
    "children": [
      {
        "asian_color": "#f4a582",
        "asian_ej_efficiency": 0.2261839828,
        "black_color": "#d6604d",
        "black_ej_efficiency": 0.4587862082,
        "code": "AA",
        "fracTotalConc": 0.2008585273,
        "latino_color": "#f4a582",
        "latino_ej_efficiency": 0.3489482259,
        "name": "Degreasing",
        "nw_color": "#f4a582",
        "nw_ej_efficiency": 0.3455736669
      },
      {
        "asian_color": "#d6604d",
        "asian_ej_efficiency": 0.4535152498,
        "black_color": "#67001f",
        "black_ej_efficiency": 1.5442365623,
        "code": "AA",
        "fracTotalConc": 0.0100378059,
        "latino_color": "#f4a582",
        "latino_ej_efficiency": 0.3661427854,
        "name": "Dry Cleaning",
        "nw_color": "#b2182b",
        "nw_ej_efficiency": 0.7455793763
      },
      {
        "asian_color": "#b2182b",
        "asian_ej_efficiency": 0.6406805954,
        "black_color": "#f4a582",
        "black_ej_efficiency": 0.2923014537,
        "code": "AA",
        "fracTotalConc": 0.4916144407,
        "latino_color": "#d6604d",
        "latino_ej_efficiency": 0.5668706171,
        "name": "Graphic Arts",
        "nw_color": "#d6604d",
        "nw_ej_efficiency": 0.449769744
      },
      {
        "asian_color": "#f4a582",
        "asian_ej_efficiency": 0.271512702,
        "black_color": "#d6604d",
        "black_ej_efficiency": 0.4251346807,
        "code": "AA",
        "fracTotalConc": 1.6853392424,
        "latino_color": "#d6604d",
        "latino_ej_efficiency": 0.4429934905,
        "name": "Nonindustrial",
        "nw_color": "#f4a582",
        "nw_ej_efficiency": 0.3852482442
      },
      {
        "asian_color": "#67001f",
        "asian_ej_efficiency": 0.9884243986,
        "black_color": "#d1e5f0",
        "black_ej_efficiency": -0.0041844164,
        "code": "AA",
        "fracTotalConc": 0.0319980437,
        "latino_color": "#67001f",
        "latino_ej_efficiency": 1.1092844865,
        "name": "Other Industrial",
        "nw_color": "#b2182b",
        "nw_ej_efficiency": 0.6572334671
      },
      {
        "asian_color": "#fddbc7",
        "asian_ej_efficiency": 0.0196229325,
        "black_color": "#d6604d",
        "black_ej_efficiency": 0.5672717134,
        "code": "AA",
        "fracTotalConc": 0.0001618933,
        "latino_color": "#b2182b",
        "latino_ej_efficiency": 0.6681053613,
        "name": "Solvent Utilization NEC",
        "nw_color": "#d6604d",
        "nw_ej_efficiency": 0.4880642583
      },
      {
        "asian_color": "#b2182b",
        "asian_ej_efficiency": 0.6628424649,
        "black_color": "#d6604d",
        "black_ej_efficiency": 0.4141321962,
        "code": "AA",
        "fracTotalConc": 1.1353647993,
        "latino_color": "#b2182b",
        "latino_ej_efficiency": 0.6142699131,
        "name": "Surface Coating",
        "nw_color": "#d6604d",
        "nw_ej_efficiency": 0.515310531
      }
    ],
    "name": "Solvent Utilization"
  },
  {
    "children": [
      {
        "asian_color": "#fddbc7",
        "asian_ej_efficiency": 0.1276949965,
        "black_color": "#f4a582",
        "black_ej_efficiency": 0.3138893049,
        "code": "AA",
        "fracTotalConc": 0.139932117,
        "latino_color": "#f4a582",
        "latino_ej_efficiency": 0.3614483198,
        "name": "Bulk Materials Storage",
        "nw_color": "#f4a582",
        "nw_ej_efficiency": 0.2883910033
      },
      {
        "asian_color": "#fddbc7",
        "asian_ej_efficiency": 0.0739411938,
        "black_color": "#d6604d",
        "black_ej_efficiency": 0.5205227018,
        "code": "AA",
        "fracTotalConc": 0.0039559064,
        "latino_color": "#f4a582",
        "latino_ej_efficiency": 0.356799435,
        "name": "Bulk Materials Transport",
        "nw_color": "#f4a582",
        "nw_ej_efficiency": 0.341041884
      },
      {
        "asian_color": "#fddbc7",
        "asian_ej_efficiency": 0.1774059295,
        "black_color": "#b2182b",
        "black_ej_efficiency": 0.6013715347,
        "code": "AA",
        "fracTotalConc": 0.1012778199,
        "latino_color": "#f4a582",
        "latino_ej_efficiency": 0.3585192501,
        "name": "Bulk Terminals & Plants",
        "nw_color": "#f4a582",
        "nw_ej_efficiency": 0.3987615082
      },
      {
        "asian_color": "#67001f",
        "asian_ej_efficiency": 2.350664317,
        "black_color": "#f4a582",
        "black_ej_efficiency": 0.2585434603,
        "code": "AA",
        "fracTotalConc": 0.2342287564,
        "latino_color": "#67001f",
        "latino_ej_efficiency": 2.5468189726,
        "name": "Inorganic Chemical Storage",
        "nw_color": "#67001f",
        "nw_ej_efficiency": 1.6001188076
      },
      {
        "asian_color": "#2166ac",
        "asian_ej_efficiency": -0.6152591126,
        "black_color": "#92c5de",
        "black_ej_efficiency": -0.2842062488,
        "code": "AA",
        "fracTotalConc": 0.000339425,
        "latino_color": "#4393c3",
        "latino_ej_efficiency": -0.5628548032,
        "name": "Inorganic Chemical Transport",
        "nw_color": "#4393c3",
        "nw_ej_efficiency": -0.4409892652
      },
      {
        "asian_color": "#d6604d",
        "asian_ej_efficiency": 0.5007978572,
        "black_color": "#f4a582",
        "black_ej_efficiency": 0.3944332326,
        "code": "AA",
        "fracTotalConc": 0.0251376482,
        "latino_color": "#67001f",
        "latino_ej_efficiency": 0.9616469919,
        "name": "Organic Chemical Storage",
        "nw_color": "#b2182b",
        "nw_ej_efficiency": 0.6496873587
      },
      {
        "asian_color": "#b2182b",
        "asian_ej_efficiency": 0.6220563597,
        "black_color": "#b2182b",
        "black_ej_efficiency": 0.6887942879,
        "code": "AA",
        "fracTotalConc": 0.0022498124,
        "latino_color": "#b2182b",
        "latino_ej_efficiency": 0.7571807892,
        "name": "Organic Chemical Transport",
        "nw_color": "#b2182b",
        "nw_ej_efficiency": 0.6625011516
      },
      {
        "asian_color": "#d6604d",
        "asian_ej_efficiency": 0.5779155672,
        "black_color": "#d6604d",
        "black_ej_efficiency": 0.5028765034,
        "code": "AA",
        "fracTotalConc": 0.112989139,
        "latino_color": "#d6604d",
        "latino_ej_efficiency": 0.4611423117,
        "name": "Petroleum & Petroleum Product Storage",
        "nw_color": "#d6604d",
        "nw_ej_efficiency": 0.4619163689
      },
      {
        "asian_color": "#b2182b",
        "asian_ej_efficiency": 0.7481702686,
        "black_color": "#d6604d",
        "black_ej_efficiency": 0.5618650381,
        "code": "AA",
        "fracTotalConc": 0.2176864023,
        "latino_color": "#67001f",
        "latino_ej_efficiency": 0.8525106333,
        "name": "Petroleum & Petroleum Product Transport",
        "nw_color": "#b2182b",
        "nw_ej_efficiency": 0.6829117666
      },
      {
        "asian_color": "#f4a582",
        "asian_ej_efficiency": 0.2279837176,
        "black_color": "#d6604d",
        "black_ej_efficiency": 0.5813130855,
        "code": "AA",
        "fracTotalConc": 0.0683944039,
        "latino_color": "#f4a582",
        "latino_ej_efficiency": 0.2878909846,
        "name": "Service Stations: Breathing & Emptying",
        "nw_color": "#f4a582",
        "nw_ej_efficiency": 0.3570207179
      },
      {
        "asian_color": "#fddbc7",
        "asian_ej_efficiency": 0.0350220938,
        "black_color": "#d6604d",
        "black_ej_efficiency": 0.4341686771,
        "code": "AA",
        "fracTotalConc": 0.1514312891,
        "latino_color": "#f4a582",
        "latino_ej_efficiency": 0.3352218371,
        "name": "Service Stations: Stage I",
        "nw_color": "#f4a582",
        "nw_ej_efficiency": 0.3067853294
      },
      {
        "asian_color": "#d6604d",
        "asian_ej_efficiency": 0.4028193836,
        "black_color": "#fddbc7",
        "black_ej_efficiency": 0.0113814289,
        "code": "AA",
        "fracTotalConc": 0.0286439388,
        "latino_color": "#b2182b",
        "latino_ej_efficiency": 0.6430519316,
        "name": "Service Stations: Stage II",
        "nw_color": "#f4a582",
        "nw_ej_efficiency": 0.3679461338
      }
    ],
    "name": "Storage & Transport"
  },
  {
    "children": [
      {
        "asian_color": "#b2182b",
        "asian_ej_efficiency": 0.6193326099,
        "black_color": "#b2182b",
        "black_ej_efficiency": 0.7746310434,
        "code": "AA",
        "fracTotalConc": 0.2131600876,
        "latino_color": "#d6604d",
        "latino_ej_efficiency": 0.4351249488,
        "name": "Incineration",
        "nw_color": "#d6604d",
        "nw_ej_efficiency": 0.5350308731
      },
      {
        "asian_color": "#92c5de",
        "asian_ej_efficiency": -0.2533956566,
        "black_color": "#67001f",
        "black_ej_efficiency": 0.9501885413,
        "code": "AA",
        "fracTotalConc": 0.0097578159,
        "latino_color": "#fddbc7",
        "latino_ej_efficiency": 0.0843295919,
        "name": "Industrial Waste Water",
        "nw_color": "#f4a582",
        "nw_ej_efficiency": 0.3069348373
      },
      {
        "asian_color": "#67001f",
        "asian_ej_efficiency": 1.2408249209,
        "black_color": "#d1e5f0",
        "black_ej_efficiency": -0.0426452317,
        "code": "AA",
        "fracTotalConc": 0.1786331769,
        "latino_color": "#67001f",
        "latino_ej_efficiency": 1.0670895058,
        "name": "Landfills",
        "nw_color": "#b2182b",
        "nw_ej_efficiency": 0.6604322721
      },
      {
        "asian_color": "#b2182b",
        "asian_ej_efficiency": 0.7076849207,
        "black_color": "#f4a582",
        "black_ej_efficiency": 0.2499792882,
        "code": "AA",
        "fracTotalConc": 3.9851375965,
        "latino_color": "#d6604d",
        "latino_ej_efficiency": 0.5248107594,
        "name": "Open Burning",
        "nw_color": "#d6604d",
        "nw_ej_efficiency": 0.4314911537
      },
      {
        "asian_color": "#67001f",
        "asian_ej_efficiency": 2.4566721351,
        "black_color": "#d1e5f0",
        "black_ej_efficiency": -0.0957086205,
        "code": "AA",
        "fracTotalConc": 0.3986764037,
        "latino_color": "#67001f",
        "latino_ej_efficiency": 2.1438549194,
        "name": "Other",
        "nw_color": "#67001f",
        "nw_ej_efficiency": 1.3108972842
      },
      {
        "asian_color": "#f4a582",
        "asian_ej_efficiency": 0.32669791,
        "black_color": "#b2182b",
        "black_ej_efficiency": 0.7584748351,
        "code": "AA",
        "fracTotalConc": 0.0761628879,
        "latino_color": "#f4a582",
        "latino_ej_efficiency": 0.3124197629,
        "name": "POTW",
        "nw_color": "#d6604d",
        "nw_ej_efficiency": 0.4378631308
      },
      {
        "asian_color": "#67001f",
        "asian_ej_efficiency": 1.0101271061,
        "black_color": "#fddbc7",
        "black_ej_efficiency": 0.0169894859,
        "code": "AA",
        "fracTotalConc": 0.0090484531,
        "latino_color": "#67001f",
        "latino_ej_efficiency": 1.3974652502,
        "name": "TSDF",
        "nw_color": "#67001f",
        "nw_ej_efficiency": 0.8090205818
      }
    ],
    "name": "Waste Disposal & Recycling"    
    }
]
}
